ipfslib/__init__.py
ipfslib/connect.py
ipfslib/IPFS/__init__.py
ipfslib/IPFS/add.py
ipfslib/IPFS/cat.py
ipfslib/IPFS/get.py
ipfslib/IPFS/rem.py
ipfslib/IPFS/resolve.py
ipfslib/Key/__init__.py
ipfslib/Key/generate.py
ipfslib/Key/list.py
ipfslib/Key/publish.py
ipfslib/Key/remove.py
ipfslib/Key/rename.py
ipfslib-0.1.10.dist-info/METADATA
ipfslib-0.1.10.dist-info/WHEEL
ipfslib-0.1.10.dist-info/top_level.txt
ipfslib-0.1.10.dist-info/RECORD
