Metadata-Version: 2.1
Name: ipfslib
Version: 0.1.10
Summary: IPFS Library for Python
Author: Christian Remboldt
Author-email: christian@remboldt.eu
Keywords: python,ipfs,api,decentral,networking,ipns,web3
Classifier: Programming Language :: Python :: 3
